pmda/__init__.py
pmda/_version.py
pmda/contacts.py
pmda/custom.py
pmda/density.py
pmda/leaflet.py
pmda/parallel.py
pmda/rdf.py
pmda/rms.py
pmda/util.py
pmda/rms/__init__.py
pmda/rms/rmsd.py
pmda/rms/rmsf.py
pmda-0.3.0.dist-info/AUTHORS
pmda-0.3.0.dist-info/LICENSE
pmda-0.3.0.dist-info/METADATA
pmda-0.3.0.dist-info/WHEEL
pmda-0.3.0.dist-info/top_level.txt
pmda-0.3.0.dist-info/RECORD
