Metadata-Version: 2.1
Name: pmda
Version: 0.3.0
Summary: Parallel Molecular Dynamics Analysis tools
Home-page: https://github.com/MDAnalysis/pmda/
Author: Max Linke
Author-email: max.linke88@gmail.com
License: GPLv2
Download-URL: https://github.com/MDAnalysis/pmda/releases
Project-URL: Documentation, https://www.mdanalysis.org/pmda/
Project-URL: Source, https://github.com/MDAnalysis/pmda/
Project-URL: Issue Tracker, https://github.com/MDAnalysis/pmda/issues/
Project-URL: Mailing list, https://groups.google.com/group/mdnalysis-discussion
Keywords: science parallel
Platform: UNKNOWN
Classifier: Development Status :: 3 - Alpha
Classifier: Environment :: Console
Classifier: Intended Audience :: Science/Research
Classifier: License :: OSI Approved :: GNU General Public License v2 (GPLv2)
Classifier: Programming Language :: Python
Classifier: Topic :: Scientific/Engineering
Classifier: Topic :: Software Development :: Libraries :: Python Modules
Classifier: Programming Language :: Python :: 2
Classifier: Programming Language :: Python :: 2.7
Classifier: Programming Language :: Python :: 3
Classifier: Programming Language :: Python :: 3.4
Classifier: Programming Language :: Python :: 3.5
Classifier: Programming Language :: Python :: 3.6
Requires-Dist: MDAnalysis (>=0.19.0)
Requires-Dist: dask (>=0.18)
Requires-Dist: distributed
Requires-Dist: six
Requires-Dist: joblib
Requires-Dist: networkx
Requires-Dist: scipy
